{
  "miniprogramRoot": "miniprogram/",
  "cloudfunctionRoot": "cloudfunctions/",
  "compileType": "miniprogram",
  "appid": "wxe91303325b9f2178",
  "projectname": "捷克租房助手",
  "libVersion": "latest",
  "setting": {
    "es6": true,
    "enhance": true,
    "postcss": true,
    "minified": true,
    "packNpmManually": false,
    "compileWorklet": false,
    "uglifyFileName": false,
    "uploadWithSourceMap": true,
    "packNpmRelationList": [],
    "minifyWXSS": true,
    "minifyWXML": true,
    "localPlugins": false,
    "disableUseStrict": false,
    "useCompilerPlugins": false,
    "condition": false,
    "swc": false,
    "disableSWC": true,
    "babelSetting": {
      "ignore": [],
      "disablePlugins": [],
      "outputPath": ""
    }
  },
  "packOptions": {
    "ignore": [
      {
        "value": "docs",
        "type": "folder"
      },
      {
        "value": "README.md",
        "type": "file"
      }
    ],
    "include": []
  },
  "simulatorPluginLibVersion": {},
  "editorSetting": {}
}